cvedb/__init__.py
cvedb/cvedb.py
cvedb/nvdapi.py
cvedb/version.py
cvedb/cvetools/CVEComponents.py
cvedb/cvetools/CVEHandler.py
cvedb/cvetools/CVEListHandler.py
cvedb/cvetools/__init__.py
cvedb/utils/__init__.py
cvedb/utils/argsutils.py
cvedb/utils/pathutils.py
cvedb/utils/pickleutils.py
cvedb/utils/pipeutils.py
py_cvedb-0.0.5.post2.dist-info/METADATA
py_cvedb-0.0.5.post2.dist-info/WHEEL
py_cvedb-0.0.5.post2.dist-info/entry_points.txt
py_cvedb-0.0.5.post2.dist-info/top_level.txt
py_cvedb-0.0.5.post2.dist-info/RECORD
