Metadata-Version: 2.1
Name: py-cvedb
Version: 0.0.5.post2
Summary: A simple CVE database written in Python
Home-page: https://github.com/BoxHezi/cvedb
Author: Box Hezi
Author-email: hezipypi.yixdpu@bumpmail.io
Requires-Dist: nvdlib
Requires-Dist: tqdm
Requires-Dist: pgzip
Requires-Dist: GitPython
